{
  "manifestVersion": 1,
  "id": "querytile-extended",
  "version": "0.1.78",
  "name": "Query Tile Extended",
  "description": "Query Tile extended wih aggregation function",
  "publisher": "aurelien-sudre",
  "scopes": ["vso.work"],
  "targets": [
    {
      "id": "Microsoft.VisualStudio.Services"
    }
  ],
  "icons": {
    "default": "images/logo.png"
  },
  "demands": ["contribution/ms.vss-dashboards-web.widget-sdk-version-2"],
  "contributions": [
    {
      "id": "querytile-extended-widget",
      "type": "ms.vss-dashboards-web.widget",
      "targets": [
        "ms.vss-dashboards-web.widget-catalog",
        ".querytile-extended-widget-configuration"
      ],
      "properties": {
        "name": "Query Tile Extended",
        "description": "Query Tile Widget extended with aggregation function",
        "catalogIconUrl:": "images/logo.png",
        "previewImageUrl": "images/logo.png",
        "uri": "widget.html",
        "isNameConfigurable": true,
        "supportedSizes": [
          {
            "rowSpan": 1,
            "columnSpan": 1
          }
        ],
        "supportedScopes": [
          "project_team"
        ]
      }
    },
    {
      "id": "querytile-extended-widget-configuration",
      "type": "ms.vss-dashboards-web.widget-configuration",
      "targets": [
        "ms.vss-dashboards-web.widget-configuration"
      ],
      "properties": {
        "name": "Query Tile Extended Configuration",
        "description": "Query Tile Widget extended with aggregation function",
        "uri": "configuration.html"
      }
    }
  ],
  "files": [
    {
      "path": "widget.html",
      "addressable": true
    },
    {
      "path": "configuration.html",
      "addressable": true
    },
    {
      "path": "bower_components/vss-web-extension-sdk/lib/VSS.SDK.min.js",
      "addressable": true
    },
    {
      "path": "images",
      "addressable": true
    }
  ]
}